dynetlsm/__init__.py
dynetlsm/array_utils.py
dynetlsm/case_control_likelihood.py
dynetlsm/directed_likelihoods_fast.c
dynetlsm/directed_likelihoods_fast.cpython-37m-darwin.so
dynetlsm/distributions.py
dynetlsm/gaussian_likelihood_fast.c
dynetlsm/gaussian_likelihood_fast.cpython-37m-darwin.so
dynetlsm/hdp_lpcm.py
dynetlsm/imputer.py
dynetlsm/label_utils.py
dynetlsm/latent_space.py
dynetlsm/lsm.py
dynetlsm/metrics.py
dynetlsm/metropolis.py
dynetlsm/network_likelihoods.py
dynetlsm/network_statistics.py
dynetlsm/plots.py
dynetlsm/procrustes.py
dynetlsm/sample_auxillary.py
dynetlsm/sample_coefficients.py
dynetlsm/sample_concentration.py
dynetlsm/sample_labels.py
dynetlsm/sample_latent_positions.py
dynetlsm/static_network_fast.c
dynetlsm/static_network_fast.cpython-37m-darwin.so
dynetlsm/text_utils.py
dynetlsm/trace_utils.py
dynetlsm/version.py
dynetlsm/datasets/__init__.py
dynetlsm/datasets/load_alliances.py
dynetlsm/datasets/load_got.py
dynetlsm/datasets/load_monks.py
dynetlsm/datasets/samples_generator.py
dynetlsm/datasets/raw_data/sampson.npy
dynetlsm/datasets/raw_data/sampson_0.npy
dynetlsm/datasets/raw_data/sampson_1.npy
dynetlsm/datasets/raw_data/sampson_2.npy
dynetlsm/datasets/raw_data/sampson_groups.txt
dynetlsm/datasets/raw_data/sampson_groups_waverers.txt
dynetlsm/datasets/raw_data/sampson_names.txt
dynetlsm/datasets/raw_data/got/got-s1-edges.csv
dynetlsm/datasets/raw_data/got/got-s1-nodes.csv
dynetlsm/datasets/raw_data/got/got-s2-edges.csv
dynetlsm/datasets/raw_data/got/got-s2-nodes.csv
dynetlsm/datasets/raw_data/got/got-s3-edges.csv
dynetlsm/datasets/raw_data/got/got-s3-nodes.csv
dynetlsm/datasets/raw_data/got/got-s4-edges.csv
dynetlsm/datasets/raw_data/got/got-s4-nodes.csv
dynetlsm/datasets/raw_data/got/got-s5-edges.csv
dynetlsm/datasets/raw_data/got/got-s5-node.csv
dynetlsm/datasets/raw_data/got/got-s6-edges.csv
dynetlsm/datasets/raw_data/got/got-s6-nodes.csv
dynetlsm/datasets/raw_data/got/got-s7-edges.csv
dynetlsm/datasets/raw_data/got/got-s7-nodes.csv
dynetlsm-0.1.0.dist-info/LICENSE
dynetlsm-0.1.0.dist-info/METADATA
dynetlsm-0.1.0.dist-info/WHEEL
dynetlsm-0.1.0.dist-info/top_level.txt
dynetlsm-0.1.0.dist-info/RECORD
