Metadata-Version: 2.1
Name: dynetlsm
Version: 0.1.0
Summary: dynetlsm
Home-page: https://joshloyal.github.io/dynetlsm
Maintainer: Joshua D. Loyal
Maintainer-email: jloyal25@gmail.com
License: MIT
Download-URL: https://pypi.org/project/dynetlsm/#files
Platform: UNKNOWN
Requires-Dist: cython
Requires-Dist: scipy
Requires-Dist: numpy
Requires-Dist: scikit-learn
Requires-Dist: tqdm
Requires-Dist: networkx
Requires-Dist: pandas
Requires-Dist: plac
Requires-Dist: joblib
Requires-Dist: matplotlib
Requires-Dist: seaborn
Requires-Dist: arviz
Requires-Dist: pyvis
Requires-Dist: statsmodels
Provides-Extra: test
Requires-Dist: pytest ; extra == 'test'
Requires-Dist: pytest-pep8 ; extra == 'test'
Requires-Dist: pytest-cov ; extra == 'test'
